odoo/addons/l10n_es_facturae_efact/README.rst
odoo/addons/l10n_es_facturae_efact/__init__.py
odoo/addons/l10n_es_facturae_efact/__manifest__.py
odoo/addons/l10n_es_facturae_efact/data/efact_data.xml
odoo/addons/l10n_es_facturae_efact/i18n/es.po
odoo/addons/l10n_es_facturae_efact/i18n/l10n_es_facturae_efact.pot
odoo/addons/l10n_es_facturae_efact/models/__init__.py
odoo/addons/l10n_es_facturae_efact/models/account_invoice_integration.py
odoo/addons/l10n_es_facturae_efact/models/account_invoice_integration_log.py
odoo/addons/l10n_es_facturae_efact/models/account_invoice_integration_method.py
odoo/addons/l10n_es_facturae_efact/models/config.py
odoo/addons/l10n_es_facturae_efact/models/res_company.py
odoo/addons/l10n_es_facturae_efact/models/res_partner.py
odoo/addons/l10n_es_facturae_efact/static/description/icon.png
odoo/addons/l10n_es_facturae_efact/tests/__init__.py
odoo/addons/l10n_es_facturae_efact/tests/result.xml
odoo/addons/l10n_es_facturae_efact/tests/result_02.xml
odoo/addons/l10n_es_facturae_efact/tests/test_efact.py
odoo/addons/l10n_es_facturae_efact/views/account_invoice_integration_view.xml
odoo/addons/l10n_es_facturae_efact/views/res_company_view.xml
odoo/addons/l10n_es_facturae_efact/views/res_config_views.xml
odoo/addons/l10n_es_facturae_efact/views/res_partner_view.xml
odoo11_addon_l10n_es_facturae_efact-11.0.1.0.2.dist-info/METADATA
odoo11_addon_l10n_es_facturae_efact-11.0.1.0.2.dist-info/RECORD
odoo11_addon_l10n_es_facturae_efact-11.0.1.0.2.dist-info/WHEEL
odoo11_addon_l10n_es_facturae_efact-11.0.1.0.2.dist-info/top_level.txt
